[
  {
    "date": "9 Jul 2026",
    "summary": "Combined summary unavailable today \u2014 API error."
  },
  {
    "date": "10 Jul 2026",
    "summary": "Combined summary unavailable today \u2014 API error."
  },
  {
    "date": "11 Jul 2026",
    "summary": "Combined summary unavailable today \u2014 API error."
  },
  {
    "date": "12 Jul 2026",
    "summary": "Combined summary unavailable today \u2014 API error."
  },
  {
    "date": "13 Jul 2026",
    "summary": "Combined summary unavailable today \u2014 API error."
  },
  {
    "date": "14 Jul 2026",
    "summary": "Combined summary unavailable today \u2014 API error."
  },
  {
    "date": "16 Jul 2026",
    "summary": "Combined summary unavailable today \u2014 API error."
  }
]