[
  {
    "date": "17 Apr 2026",
    "summary": "Combined summary unavailable today \u2014 API error."
  },
  {
    "date": "18 Apr 2026",
    "summary": "Combined summary unavailable today \u2014 API error."
  },
  {
    "date": "19 Apr 2026",
    "summary": "Combined summary unavailable today \u2014 API error."
  },
  {
    "date": "20 Apr 2026",
    "summary": "Combined summary unavailable today \u2014 API error."
  },
  {
    "date": "21 Apr 2026",
    "summary": "Combined summary unavailable today \u2014 API error."
  },
  {
    "date": "22 Apr 2026",
    "summary": "Combined summary unavailable today \u2014 API error."
  },
  {
    "date": "23 Apr 2026",
    "summary": "Combined summary unavailable today \u2014 API error."
  }
]